my_goto_logger/__init__.py
my_goto_logger-0.1.0.dist-info/licenses/LICENSE
my_goto_logger-0.1.0.dist-info/METADATA
my_goto_logger-0.1.0.dist-info/WHEEL
my_goto_logger-0.1.0.dist-info/top_level.txt
my_goto_logger-0.1.0.dist-info/RECORD
